LICENSE
README.md
setup.cfg
setup.py
ironhawks_keygen.egg-info/PKG-INFO
ironhawks_keygen.egg-info/SOURCES.txt
ironhawks_keygen.egg-info/dependency_links.txt
ironhawks_keygen.egg-info/top_level.txt
ironhawkskeygen/__init__.py
ironhawkskeygen/example.py
ironhawkskeygen/keygen.py
ironhawkskeygen/strict_checks.py