Metadata-Version: 2.1
Name: ironhawks-keygen
Version: 0.2.1
Summary: Effortlessly generate random passwords of custom lengths.
Home-page: https://github.com/hartbrkr3399/ironhawks-keygen
Author: Praveen K
Author-email: hartbrkrlegacy@gmail.com
License: MIT
Download-URL: https://github.com/hartbrkr3399/ironhawks-keygen/archive/refs/tags/v0.2.1.tar.gz
Keywords: password,keygen,random
Platform: UNKNOWN
Classifier: Development Status :: 5 - Production/Stable
Classifier: Intended Audience :: Developers
Classifier: Intended Audience :: End Users/Desktop
Classifier: Topic :: Software Development :: Libraries :: Python Modules
Classifier: License :: OSI Approved :: MIT License
Classifier: Programming Language :: Python :: 3
Classifier: Programming Language :: Python :: 3.6
Classifier: Programming Language :: Python :: 3.7
Classifier: Programming Language :: Python :: 3.8
